example_pkg/__init__.py
nuc_fwhm-0.0.1.dist-info/LICENSE
nuc_fwhm-0.0.1.dist-info/METADATA
nuc_fwhm-0.0.1.dist-info/WHEEL
nuc_fwhm-0.0.1.dist-info/top_level.txt
nuc_fwhm-0.0.1.dist-info/RECORD
