Metadata-Version: 2.1
Name: nuc-fwhm
Version: 0.0.1
Summary: Full Width at Half Maximum(F.W.H.M.)
Home-page: https://github.com/Rohan-LK/nuclear_fwhm
Author: Rohan Lal Kshetry
Author-email: rlkshetry95@gmail.com
License: UNKNOWN
Platform: UNKNOWN
Classifier: Programming Language :: Python :: 3
Classifier: License :: OSI Approved :: MIT License
Classifier: Operating System :: OS Independent
Requires-Python: >=3.0
